cvScore/__init__.py
cvScore/__main__.py
cvScore/classes/ScoredDoc.py
cvScore/classes/__init__.py
cvScore/commands.py
cvscore-0.1.3.dist-info/LICENSE
cvscore-0.1.3.dist-info/METADATA
cvscore-0.1.3.dist-info/WHEEL
cvscore-0.1.3.dist-info/entry_points.txt
cvscore-0.1.3.dist-info/RECORD
