Metadata-Version: 2.1
Name: cvScore
Version: 0.1.3
Summary: A CLI application that scores CVs using keywords.
Author: Philip Glebow
Author-email: 11603439+pglebow@users.noreply.github.com
Requires-Python: >=3.9,<4.0
Classifier: Programming Language :: Python :: 3
Classifier: Programming Language :: Python :: 3.9
Classifier: Programming Language :: Python :: 3.10
Classifier: Programming Language :: Python :: 3.11
Classifier: Programming Language :: Python :: 3.12
Requires-Dist: click (>=8.1.7,<9.0.0)
Requires-Dist: docx (>=0.2.4,<0.3.0)
Requires-Dist: filetype (>=1.2.0,<2.0.0)
Requires-Dist: lxml (>=5.2.1,<6.0.0)
Requires-Dist: pypdf (>=4.2.0,<5.0.0)
Requires-Dist: python-docx (>=1.1.0,<2.0.0)
